[{"Ticker":"MIRM","Contract Name":"MIRM251017P00050000","Type":"Put","Expiry":"2025-10-17T00:00:00.000","Strike":50.0,"Moneyness":0.6577807511,"Bid":0.85,"Ask":5.5,"Volume":1,"Open Interest":6,"Bid Stock":75.39,"Ask Stock":75.62,"Last Stock Price":75.5299987793,"Implied Volatility":1.2907750305,"Expiry_dt":"2025-10-17T00:00:00.000","Years_to_Expiry":0.1341546886,"Forward":76.0131699171,"LogMoneyness":-0.4188836082,"IV_bid":0.8689869649,"IV_ask":1.6923070798,"IV_mid":1.3315700902,"IV_spread":0.8233201149,"Delta":-0.1350730981,"Ivol\/Rvol100d Ratio":3.0991884531,"Smoothed_IV":1.3315700902,"TotalVariance":0.2378668483,"Call Local Vol":null,"Put Local Vol":0.382212272,"Realised Vol 100d":0.4296512169},{"Ticker":"MIRM","Contract Name":"MIRM251017P00045000","Type":"Put","Expiry":"2025-10-17T00:00:00.000","Strike":45.0,"Moneyness":0.592002676,"Bid":0.9,"Ask":5.5,"Volume":1,"Open Interest":8,"Bid Stock":75.39,"Ask Stock":75.62,"Last Stock Price":75.5299987793,"Implied Volatility":1.5239281616,"Expiry_dt":"2025-10-17T00:00:00.000","Years_to_Expiry":0.1341546886,"Forward":76.0131699171,"LogMoneyness":-0.5242441239,"IV_bid":1.0570598979,"IV_ask":1.9673511034,"IV_mid":1.5696888862,"IV_spread":0.9102912055,"Delta":-0.1152051322,"Ivol\/Rvol100d Ratio":3.6534026312,"Smoothed_IV":1.5696888862,"TotalVariance":0.3305468495,"Call Local Vol":null,"Put Local Vol":0.0,"Realised Vol 100d":0.4296512169},{"Ticker":"MIRM","Contract Name":"MIRM250919P00045000","Type":"Put","Expiry":"2025-09-19T00:00:00.000","Strike":45.0,"Moneyness":0.5942761713,"Bid":0.0,"Ask":5.0,"Volume":0,"Open Interest":27,"Bid Stock":75.39,"Ask Stock":75.62,"Last Stock Price":75.5299987793,"Implied Volatility":2.0742235645,"Expiry_dt":"2025-09-19T00:00:00.000","Years_to_Expiry":0.0574948665,"Forward":75.7223697863,"LogMoneyness":-0.5204111328,"IV_bid":null,"IV_ask":2.8641529531,"IV_mid":2.1794884098,"IV_spread":null,"Delta":-0.1043565231,"Ivol\/Rvol100d Ratio":5.0726922774,"Smoothed_IV":2.1794884098,"TotalVariance":0.2731103745,"Call Local Vol":null,"Put Local Vol":0.0,"Realised Vol 100d":0.4296512169},{"Ticker":"MIRM","Contract Name":"MIRM251219C00080000","Type":"Call","Expiry":"2025-12-19T00:00:00.000","Strike":80.0,"Moneyness":1.0434116647,"Bid":2.1,"Ask":7.0,"Volume":10,"Open Interest":10,"Bid Stock":75.39,"Ask Stock":75.62,"Last Stock Price":75.5299987793,"Implied Volatility":0.5245408875,"Expiry_dt":"2025-12-19T00:00:00.000","Years_to_Expiry":0.3066392882,"Forward":76.6715599487,"LogMoneyness":0.042495791,"IV_bid":0.2053518531,"IV_ask":0.5027427321,"IV_mid":0.3555154289,"IV_spread":0.2973908789,"Delta":0.4532607172,"Ivol\/Rvol100d Ratio":0.8274512325,"Smoothed_IV":0.3555154289,"TotalVariance":0.0387565138,"Call Local Vol":0.482282982,"Put Local Vol":null,"Realised Vol 100d":0.4296512169},{"Ticker":"MIRM","Contract Name":"MIRM251219P00075000","Type":"Put","Expiry":"2025-12-19T00:00:00.000","Strike":75.0,"Moneyness":0.9781984356,"Bid":3.5,"Ask":8.0,"Volume":5,"Open Interest":5,"Bid Stock":75.39,"Ask Stock":75.62,"Last Stock Price":75.5299987793,"Implied Volatility":0.4940236145,"Expiry_dt":"2025-12-19T00:00:00.000","Years_to_Expiry":0.3066392882,"Forward":76.6715599487,"LogMoneyness":-0.0220427301,"IV_bid":0.2592105167,"IV_ask":0.5352756844,"IV_mid":0.3972268729,"IV_spread":0.2760651677,"Delta":-0.4167586594,"Ivol\/Rvol100d Ratio":0.924533336,"Smoothed_IV":0.3972268729,"TotalVariance":0.0483843644,"Call Local Vol":0.1913555141,"Put Local Vol":0.0,"Realised Vol 100d":0.4296512169},{"Ticker":"MIRM","Contract Name":"MIRM251219P00045000","Type":"Put","Expiry":"2025-12-19T00:00:00.000","Strike":45.0,"Moneyness":0.5869190614,"Bid":2.8,"Ask":7.5,"Volume":8,"Open Interest":9,"Bid Stock":75.39,"Ask Stock":75.62,"Last Stock Price":75.5299987793,"Implied Volatility":1.2407264526,"Expiry_dt":"2025-12-19T00:00:00.000","Years_to_Expiry":0.3066392882,"Forward":76.6715599487,"LogMoneyness":-0.5328683539,"IV_bid":1.0002551799,"IV_ask":1.5290772818,"IV_mid":1.2777081651,"IV_spread":0.5288221019,"Delta":-0.1341678846,"Ivol\/Rvol100d Ratio":2.9738264781,"Smoothed_IV":1.2777081651,"TotalVariance":0.5006003378,"Call Local Vol":null,"Put Local Vol":0.0,"Realised Vol 100d":0.4296512169},{"Ticker":"MIRM","Contract Name":"MIRM251219C00075000","Type":"Call","Expiry":"2025-12-19T00:00:00.000","Strike":75.0,"Moneyness":0.9781984356,"Bid":4.0,"Ask":8.8,"Volume":2,"Open Interest":8,"Bid Stock":75.39,"Ask Stock":75.62,"Last Stock Price":75.5299987793,"Implied Volatility":0.5101367346,"Expiry_dt":"2025-12-19T00:00:00.000","Years_to_Expiry":0.3066392882,"Forward":76.6715599487,"LogMoneyness":-0.0220427301,"IV_bid":0.1884644381,"IV_ask":0.4833151094,"IV_mid":0.3361717852,"IV_spread":0.2948506712,"Delta":0.5837467913,"Ivol\/Rvol100d Ratio":0.7824294963,"Smoothed_IV":0.3361717852,"TotalVariance":0.0346537565,"Call Local Vol":0.1913555141,"Put Local Vol":0.0,"Realised Vol 100d":0.4296512169},{"Ticker":"MIRM","Contract Name":"MIRM251017C00070000","Type":"Call","Expiry":"2025-10-17T00:00:00.000","Strike":70.0,"Moneyness":0.9208930515,"Bid":5.0,"Ask":9.4,"Volume":4,"Open Interest":6,"Bid Stock":75.39,"Ask Stock":75.62,"Last Stock Price":75.5299987793,"Implied Volatility":0.5772747351,"Expiry_dt":"2025-10-17T00:00:00.000","Years_to_Expiry":0.1341546886,"Forward":76.0131699171,"LogMoneyness":-0.0824113716,"IV_bid":null,"IV_ask":0.5620627314,"IV_mid":0.3225656608,"IV_spread":null,"Delta":0.7753577473,"Ivol\/Rvol100d Ratio":0.75076166,"Smoothed_IV":0.3225656608,"TotalVariance":0.0139586083,"Call Local Vol":0.1422409563,"Put Local Vol":null,"Realised Vol 100d":0.4296512169},{"Ticker":"MIRM","Contract Name":"MIRM250919C00080000","Type":"Call","Expiry":"2025-09-19T00:00:00.000","Strike":80.0,"Moneyness":1.0564909712,"Bid":0.95,"Ask":4.9,"Volume":2,"Open Interest":83,"Bid Stock":75.39,"Ask Stock":75.62,"Last Stock Price":75.5299987793,"Implied Volatility":0.6215858154,"Expiry_dt":"2025-09-19T00:00:00.000","Years_to_Expiry":0.0574948665,"Forward":75.7223697863,"LogMoneyness":0.0549530121,"IV_bid":0.3410228431,"IV_ask":0.9206089884,"IV_mid":0.641250349,"IV_spread":0.5795861453,"Delta":0.3895408487,"Ivol\/Rvol100d Ratio":1.4924904756,"Smoothed_IV":0.641250349,"TotalVariance":0.0236420047,"Call Local Vol":0.5679565344,"Put Local Vol":null,"Realised Vol 100d":0.4296512169},{"Ticker":"MIRM","Contract Name":"MIRM251219P00040000","Type":"Put","Expiry":"2025-12-19T00:00:00.000","Strike":40.0,"Moneyness":0.5217058323,"Bid":0.0,"Ask":5.0,"Volume":10,"Open Interest":989,"Bid Stock":75.39,"Ask Stock":75.62,"Last Stock Price":75.5299987793,"Implied Volatility":1.0913131372,"Expiry_dt":"2025-12-19T00:00:00.000","Years_to_Expiry":0.3066392882,"Forward":76.6715599487,"LogMoneyness":-0.6506513895,"IV_bid":null,"IV_ask":1.458914095,"IV_mid":1.1220944664,"IV_spread":null,"Delta":-0.0872602886,"Ivol\/Rvol100d Ratio":2.6116403778,"Smoothed_IV":1.1220944664,"TotalVariance":0.3860882985,"Call Local Vol":null,"Put Local Vol":0.1901171416,"Realised Vol 100d":0.4296512169},{"Ticker":"MIRM","Contract Name":"MIRM260116C00065000","Type":"Call","Expiry":"2026-01-16T00:00:00.000","Strike":65.0,"Moneyness":0.8445286948,"Bid":11.5,"Ask":16.0,"Volume":70,"Open Interest":4,"Bid Stock":75.39,"Ask Stock":75.62,"Last Stock Price":75.5299987793,"Implied Volatility":0.5673871387,"Expiry_dt":"2026-01-16T00:00:00.000","Years_to_Expiry":0.3832991102,"Forward":76.9660052984,"LogMoneyness":-0.1689765648,"IV_bid":null,"IV_ask":0.5227129284,"IV_mid":0.3614241374,"IV_spread":null,"Delta":0.8070408939,"Ivol\/Rvol100d Ratio":0.8412035698,"Smoothed_IV":0.3614241374,"TotalVariance":0.0500693689,"Call Local Vol":0.2781659393,"Put Local Vol":null,"Realised Vol 100d":0.4296512169},{"Ticker":"MIRM","Contract Name":"MIRM260116C00075000","Type":"Call","Expiry":"2026-01-16T00:00:00.000","Strike":75.0,"Moneyness":0.9744561863,"Bid":5.0,"Ask":10.0,"Volume":129,"Open Interest":127,"Bid Stock":75.39,"Ask Stock":75.62,"Last Stock Price":75.5299987793,"Implied Volatility":0.5218553674,"Expiry_dt":"2026-01-16T00:00:00.000","Years_to_Expiry":0.3832991102,"Forward":76.9660052984,"LogMoneyness":-0.0258757212,"IV_bid":0.2153258372,"IV_ask":0.490906089,"IV_mid":0.3532386538,"IV_spread":0.2755802517,"Delta":0.5900471617,"Ivol\/Rvol100d Ratio":0.8221521084,"Smoothed_IV":0.3532386538,"TotalVariance":0.0478271226,"Call Local Vol":0.0,"Put Local Vol":null,"Realised Vol 100d":0.4296512169},{"Ticker":"MIRM","Contract Name":"MIRM260417C00080000","Type":"Call","Expiry":"2026-04-17T00:00:00.000","Strike":80.0,"Moneyness":1.0265519642,"Bid":5.5,"Ask":10.2,"Volume":0,"Open Interest":128,"Bid Stock":75.39,"Ask Stock":75.62,"Last Stock Price":75.5299987793,"Implied Volatility":0.4998218964,"Expiry_dt":"2026-04-17T00:00:00.000","Years_to_Expiry":0.6324435318,"Forward":77.9307846004,"LogMoneyness":0.0262055789,"IV_bid":0.2663586327,"IV_ask":0.4629652651,"IV_mid":0.3645001732,"IV_spread":0.1966066325,"Delta":0.5217448631,"Ivol\/Rvol100d Ratio":0.8483629485,"Smoothed_IV":0.3645001732,"TotalVariance":0.0840266856,"Call Local Vol":0.3866557252,"Put Local Vol":null,"Realised Vol 100d":0.4296512169},{"Ticker":"MIRM","Contract Name":"MIRM260116C00070000","Type":"Call","Expiry":"2026-01-16T00:00:00.000","Strike":70.0,"Moneyness":0.9094924406,"Bid":8.0,"Ask":12.4,"Volume":1,"Open Interest":38,"Bid Stock":75.39,"Ask Stock":75.62,"Last Stock Price":75.5299987793,"Implied Volatility":0.5202684692,"Expiry_dt":"2026-01-16T00:00:00.000","Years_to_Expiry":0.3832991102,"Forward":76.9660052984,"LogMoneyness":-0.0948685927,"IV_bid":0.2022829788,"IV_ask":0.4824735327,"IV_mid":0.3487314583,"IV_spread":0.2801905539,"Delta":0.7079323062,"Ivol\/Rvol100d Ratio":0.8116617493,"Smoothed_IV":0.3487314583,"TotalVariance":0.0466143962,"Call Local Vol":0.2263176814,"Put Local Vol":null,"Realised Vol 100d":0.4296512169},{"Ticker":"MIRM","Contract Name":"MIRM250919C00070000","Type":"Call","Expiry":"2025-09-19T00:00:00.000","Strike":70.0,"Moneyness":0.9244295998,"Bid":5.6,"Ask":8.3,"Volume":3,"Open Interest":105,"Bid Stock":75.39,"Ask Stock":75.62,"Last Stock Price":75.5299987793,"Implied Volatility":0.6958038232,"Expiry_dt":"2025-09-19T00:00:00.000","Years_to_Expiry":0.0574948665,"Forward":75.7223697863,"LogMoneyness":-0.0785783805,"IV_bid":null,"IV_ask":0.7106991888,"IV_mid":0.4829219654,"IV_spread":null,"Delta":0.7692849924,"Ivol\/Rvol100d Ratio":1.1239860296,"Smoothed_IV":0.4829219654,"TotalVariance":0.0134085862,"Call Local Vol":0.0,"Put Local Vol":null,"Realised Vol 100d":0.4296512169},{"Ticker":"MIRM","Contract Name":"MIRM260116C00060000","Type":"Call","Expiry":"2026-01-16T00:00:00.000","Strike":60.0,"Moneyness":0.7795649491,"Bid":15.5,"Ask":20.0,"Volume":5,"Open Interest":20,"Bid Stock":75.39,"Ask Stock":75.62,"Last Stock Price":75.5299987793,"Implied Volatility":0.62634651,"Expiry_dt":"2026-01-16T00:00:00.000","Years_to_Expiry":0.3832991102,"Forward":76.9660052984,"LogMoneyness":-0.2490192725,"IV_bid":null,"IV_ask":0.5744186168,"IV_mid":0.3739161784,"IV_spread":null,"Delta":0.8832604374,"Ivol\/Rvol100d Ratio":0.8702784112,"Smoothed_IV":0.3739161784,"TotalVariance":0.0535903167,"Call Local Vol":0.3193314182,"Put Local Vol":null,"Realised Vol 100d":0.4296512169},{"Ticker":"MIRM","Contract Name":"MIRM250919C00065000","Type":"Call","Expiry":"2025-09-19T00:00:00.000","Strike":65.0,"Moneyness":0.8583989141,"Bid":8.5,"Ask":12.9,"Volume":10,"Open Interest":146,"Bid Stock":75.39,"Ask Stock":75.62,"Last Stock Price":75.5299987793,"Implied Volatility":0.8959971338,"Expiry_dt":"2025-09-19T00:00:00.000","Years_to_Expiry":0.0574948665,"Forward":75.7223697863,"LogMoneyness":-0.1526863527,"IV_bid":null,"IV_ask":0.9164925383,"IV_mid":0.2541985425,"IV_spread":null,"Delta":0.9943857215,"Ivol\/Rvol100d Ratio":0.5916392937,"Smoothed_IV":0.2541985425,"TotalVariance":0.00371514,"Call Local Vol":0.0990726019,"Put Local Vol":null,"Realised Vol 100d":0.4296512169},{"Ticker":"MIRM","Contract Name":"MIRM251219C00060000","Type":"Call","Expiry":"2025-12-19T00:00:00.000","Strike":60.0,"Moneyness":0.7825587485,"Bid":15.0,"Ask":19.5,"Volume":6,"Open Interest":26,"Bid Stock":75.39,"Ask Stock":75.62,"Last Stock Price":75.5299987793,"Implied Volatility":0.658206543,"Expiry_dt":"2025-12-19T00:00:00.000","Years_to_Expiry":0.3066392882,"Forward":76.6715599487,"LogMoneyness":-0.2451862814,"IV_bid":null,"IV_ask":0.6119946841,"IV_mid":0.3784818103,"IV_spread":null,"Delta":0.8987854162,"Ivol\/Rvol100d Ratio":0.8809047791,"Smoothed_IV":0.3784818103,"TotalVariance":0.0439256122,"Call Local Vol":0.2933306327,"Put Local Vol":null,"Realised Vol 100d":0.4296512169},{"Ticker":"MIRM","Contract Name":"MIRM251219C00065000","Type":"Call","Expiry":"2025-12-19T00:00:00.000","Strike":65.0,"Moneyness":0.8477719776,"Bid":11.0,"Ask":15.6,"Volume":1,"Open Interest":188,"Bid Stock":75.39,"Ask Stock":75.62,"Last Stock Price":75.5299987793,"Implied Volatility":0.6047402808,"Expiry_dt":"2025-12-19T00:00:00.000","Years_to_Expiry":0.3066392882,"Forward":76.6715599487,"LogMoneyness":-0.1651435737,"IV_bid":null,"IV_ask":0.5660323418,"IV_mid":0.3805164112,"IV_spread":null,"Delta":0.8130252784,"Ivol\/Rvol100d Ratio":0.8856402503,"Smoothed_IV":0.3805164112,"TotalVariance":0.0443991425,"Call Local Vol":0.0,"Put Local Vol":null,"Realised Vol 100d":0.4296512169},{"Ticker":"MIRM","Contract Name":"MIRM260417C00065000","Type":"Call","Expiry":"2026-04-17T00:00:00.000","Strike":65.0,"Moneyness":0.8340734709,"Bid":13.5,"Ask":18.0,"Volume":0,"Open Interest":80,"Bid Stock":75.39,"Ask Stock":75.62,"Last Stock Price":75.5299987793,"Implied Volatility":0.541264353,"Expiry_dt":"2026-04-17T00:00:00.000","Years_to_Expiry":0.6324435318,"Forward":77.9307846004,"LogMoneyness":-0.1814337859,"IV_bid":0.2229427016,"IV_ask":0.4857765055,"IV_mid":0.3649723349,"IV_spread":0.2628338039,"Delta":0.7794157207,"Ivol\/Rvol100d Ratio":0.8494618903,"Smoothed_IV":0.3649723349,"TotalVariance":0.0842445175,"Call Local Vol":0.3537238293,"Put Local Vol":null,"Realised Vol 100d":0.4296512169},{"Ticker":"MIRM","Contract Name":"MIRM260116C00050000","Type":"Call","Expiry":"2026-01-16T00:00:00.000","Strike":50.0,"Moneyness":0.6496374576,"Bid":24.5,"Ask":29.0,"Volume":10,"Open Interest":36,"Bid Stock":75.39,"Ask Stock":75.62,"Last Stock Price":75.5299987793,"Implied Volatility":0.557133335,"Expiry_dt":"2026-01-16T00:00:00.000","Years_to_Expiry":0.3832991102,"Forward":76.9660052984,"LogMoneyness":-0.4313408293,"IV_bid":null,"IV_ask":0.7393981056,"IV_mid":0.4140870237,"IV_spread":null,"Delta":0.9649065252,"Ivol\/Rvol100d Ratio":0.9637748188,"Smoothed_IV":0.4140870237,"TotalVariance":0.065723556,"Call Local Vol":0.9948892085,"Put Local Vol":null,"Realised Vol 100d":0.4296512169}]