[{"Ticker":"WEC","Contract Name":"WEC250919C00115000","Type":"Call","Expiry":"2025-09-19T00:00:00.000","Strike":115.0,"Moneyness":1.0727727934,"Bid":0.0,"Ask":0.15,"Volume":1.0,"Open Interest":444,"Bid Stock":109.0,"Ask Stock":111.05,"Last Stock Price":110.025,"Implied Volatility":null,"Expiry_dt":"2025-09-19T00:00:00.000","Years_to_Expiry":0.0082135524,"Forward":107.198840903,"LogMoneyness":0.0702466923,"IV_bid":null,"IV_ask":null,"IV_mid":null,"IV_spread":null,"Delta":null,"Ivol\/Rvol100d Ratio":null,"Smoothed_IV":null,"TotalVariance":null,"Call Local Vol":null,"Put Local Vol":null,"Realised Vol 100d":0.150987914,"IV_mid_binomial":null},{"Ticker":"WEC","Contract Name":"WEC251219P00092500","Type":"Put","Expiry":"2025-12-19T00:00:00.000","Strike":92.5,"Moneyness":1.9008968657,"Bid":0.4,"Ask":1.05,"Volume":3.0,"Open Interest":15,"Bid Stock":109.0,"Ask Stock":111.05,"Last Stock Price":110.025,"Implied Volatility":null,"Expiry_dt":"2025-12-19T00:00:00.000","Years_to_Expiry":0.257357974,"Forward":48.6612407384,"LogMoneyness":0.6423258094,"IV_bid":null,"IV_ask":null,"IV_mid":null,"IV_spread":null,"Delta":null,"Ivol\/Rvol100d Ratio":null,"Smoothed_IV":null,"TotalVariance":null,"Call Local Vol":null,"Put Local Vol":null,"Realised Vol 100d":0.150987914,"IV_mid_binomial":null},{"Ticker":"WEC","Contract Name":"WEC260116P00110000","Type":"Put","Expiry":"2026-01-16T00:00:00.000","Strike":110.0,"Moneyness":2.8823593183,"Bid":2.35,"Ask":4.0,"Volume":1.0,"Open Interest":4,"Bid Stock":109.0,"Ask Stock":111.05,"Last Stock Price":110.025,"Implied Volatility":null,"Expiry_dt":"2026-01-16T00:00:00.000","Years_to_Expiry":0.334017796,"Forward":38.1631808717,"LogMoneyness":1.0586091665,"IV_bid":null,"IV_ask":null,"IV_mid":null,"IV_spread":null,"Delta":null,"Ivol\/Rvol100d Ratio":null,"Smoothed_IV":null,"TotalVariance":null,"Call Local Vol":null,"Put Local Vol":null,"Realised Vol 100d":0.150987914,"IV_mid_binomial":null},{"Ticker":"WEC","Contract Name":"WEC251219P00095000","Type":"Put","Expiry":"2025-12-19T00:00:00.000","Strike":95.0,"Moneyness":1.9522724567,"Bid":0.5,"Ask":1.2,"Volume":5.0,"Open Interest":13,"Bid Stock":109.0,"Ask Stock":111.05,"Last Stock Price":110.025,"Implied Volatility":null,"Expiry_dt":"2025-12-19T00:00:00.000","Years_to_Expiry":0.257357974,"Forward":48.6612407384,"LogMoneyness":0.6689940565,"IV_bid":null,"IV_ask":null,"IV_mid":null,"IV_spread":null,"Delta":null,"Ivol\/Rvol100d Ratio":null,"Smoothed_IV":null,"TotalVariance":null,"Call Local Vol":null,"Put Local Vol":null,"Realised Vol 100d":0.150987914,"IV_mid_binomial":null},{"Ticker":"WEC","Contract Name":"WEC260417C00125000","Type":"Call","Expiry":"2026-04-17T00:00:00.000","Strike":125.0,"Moneyness":7.2154918082,"Bid":1.1,"Ask":2.35,"Volume":null,"Open Interest":10,"Bid Stock":109.0,"Ask Stock":111.05,"Last Stock Price":110.025,"Implied Volatility":null,"Expiry_dt":"2026-04-17T00:00:00.000","Years_to_Expiry":0.5831622177,"Forward":17.3238364512,"LogMoneyness":1.9762303546,"IV_bid":null,"IV_ask":null,"IV_mid":null,"IV_spread":null,"Delta":null,"Ivol\/Rvol100d Ratio":null,"Smoothed_IV":null,"TotalVariance":null,"Call Local Vol":null,"Put Local Vol":null,"Realised Vol 100d":0.150987914,"IV_mid_binomial":null},{"Ticker":"WEC","Contract Name":"WEC250919P00110000","Type":"Put","Expiry":"2025-09-19T00:00:00.000","Strike":110.0,"Moneyness":1.026130498,"Bid":0.0,"Ask":0.65,"Volume":4.0,"Open Interest":890,"Bid Stock":109.0,"Ask Stock":111.05,"Last Stock Price":110.025,"Implied Volatility":null,"Expiry_dt":"2025-09-19T00:00:00.000","Years_to_Expiry":0.0082135524,"Forward":107.198840903,"LogMoneyness":0.0257949297,"IV_bid":null,"IV_ask":null,"IV_mid":null,"IV_spread":null,"Delta":null,"Ivol\/Rvol100d Ratio":null,"Smoothed_IV":null,"TotalVariance":null,"Call Local Vol":null,"Put Local Vol":null,"Realised Vol 100d":0.150987914,"IV_mid_binomial":null},{"Ticker":"WEC","Contract Name":"WEC251017P00070000","Type":"Put","Expiry":"2025-10-17T00:00:00.000","Strike":70.0,"Moneyness":0.8325040658,"Bid":0.0,"Ask":0.25,"Volume":1.0,"Open Interest":1249,"Bid Stock":109.0,"Ask Stock":111.05,"Last Stock Price":110.025,"Implied Volatility":null,"Expiry_dt":"2025-10-17T00:00:00.000","Years_to_Expiry":0.0848733744,"Forward":84.0836734305,"LogMoneyness":-0.1833171733,"IV_bid":null,"IV_ask":null,"IV_mid":null,"IV_spread":null,"Delta":null,"Ivol\/Rvol100d Ratio":null,"Smoothed_IV":null,"TotalVariance":null,"Call Local Vol":null,"Put Local Vol":null,"Realised Vol 100d":0.150987914,"IV_mid_binomial":null},{"Ticker":"WEC","Contract Name":"WEC251219P00080000","Type":"Put","Expiry":"2025-12-19T00:00:00.000","Strike":80.0,"Moneyness":1.6440189109,"Bid":0.05,"Ask":2.3,"Volume":1.0,"Open Interest":1117,"Bid Stock":109.0,"Ask Stock":111.05,"Last Stock Price":110.025,"Implied Volatility":null,"Expiry_dt":"2025-12-19T00:00:00.000","Years_to_Expiry":0.257357974,"Forward":48.6612407384,"LogMoneyness":0.4971437995,"IV_bid":null,"IV_ask":null,"IV_mid":null,"IV_spread":null,"Delta":null,"Ivol\/Rvol100d Ratio":null,"Smoothed_IV":null,"TotalVariance":null,"Call Local Vol":null,"Put Local Vol":null,"Realised Vol 100d":0.150987914,"IV_mid_binomial":null},{"Ticker":"WEC","Contract Name":"WEC251017P00097500","Type":"Put","Expiry":"2025-10-17T00:00:00.000","Strike":97.5,"Moneyness":1.159737124,"Bid":0.1,"Ask":0.3,"Volume":4.0,"Open Interest":46,"Bid Stock":109.0,"Ask Stock":111.05,"Last Stock Price":110.025,"Implied Volatility":null,"Expiry_dt":"2025-10-17T00:00:00.000","Years_to_Expiry":0.0848733744,"Forward":84.0707760284,"LogMoneyness":0.1481933622,"IV_bid":null,"IV_ask":null,"IV_mid":null,"IV_spread":null,"Delta":null,"Ivol\/Rvol100d Ratio":null,"Smoothed_IV":null,"TotalVariance":null,"Call Local Vol":null,"Put Local Vol":null,"Realised Vol 100d":0.150987914,"IV_mid_binomial":null},{"Ticker":"WEC","Contract Name":"WEC260220P00100000","Type":"Put","Expiry":"2026-02-20T00:00:00.000","Strike":100.0,"Moneyness":3.5504115684,"Bid":1.6,"Ask":2.55,"Volume":1.0,"Open Interest":5,"Bid Stock":109.0,"Ask Stock":111.05,"Last Stock Price":110.025,"Implied Volatility":null,"Expiry_dt":"2026-02-20T00:00:00.000","Years_to_Expiry":0.4298425736,"Forward":28.1657486949,"LogMoneyness":1.2670635315,"IV_bid":null,"IV_ask":null,"IV_mid":null,"IV_spread":null,"Delta":null,"Ivol\/Rvol100d Ratio":null,"Smoothed_IV":null,"TotalVariance":null,"Call Local Vol":null,"Put Local Vol":null,"Realised Vol 100d":0.150987914,"IV_mid_binomial":null},{"Ticker":"WEC","Contract Name":"WEC260116C00125000","Type":"Call","Expiry":"2026-01-16T00:00:00.000","Strike":125.0,"Moneyness":3.2754083162,"Bid":0.45,"Ask":1.0,"Volume":2.0,"Open Interest":27,"Bid Stock":109.0,"Ask Stock":111.05,"Last Stock Price":110.025,"Implied Volatility":null,"Expiry_dt":"2026-01-16T00:00:00.000","Years_to_Expiry":0.334017796,"Forward":38.1631808717,"LogMoneyness":1.186442538,"IV_bid":null,"IV_ask":null,"IV_mid":null,"IV_spread":null,"Delta":null,"Ivol\/Rvol100d Ratio":null,"Smoothed_IV":null,"TotalVariance":null,"Call Local Vol":null,"Put Local Vol":null,"Realised Vol 100d":0.150987914,"IV_mid_binomial":null},{"Ticker":"WEC","Contract Name":"WEC250919C00105000","Type":"Call","Expiry":"2025-09-19T00:00:00.000","Strike":105.0,"Moneyness":0.9795026839,"Bid":5.1,"Ask":8.0,"Volume":1.0,"Open Interest":6,"Bid Stock":109.0,"Ask Stock":111.05,"Last Stock Price":110.025,"Implied Volatility":null,"Expiry_dt":"2025-09-19T00:00:00.000","Years_to_Expiry":0.0082135524,"Forward":107.1972560447,"LogMoneyness":-0.0207103016,"IV_bid":null,"IV_ask":null,"IV_mid":null,"IV_spread":null,"Delta":null,"Ivol\/Rvol100d Ratio":null,"Smoothed_IV":null,"TotalVariance":null,"Call Local Vol":null,"Put Local Vol":null,"Realised Vol 100d":0.150987914,"IV_mid_binomial":null},{"Ticker":"WEC","Contract Name":"WEC260220C00120000","Type":"Call","Expiry":"2026-02-20T00:00:00.000","Strike":120.0,"Moneyness":4.2604938821,"Bid":1.55,"Ask":2.75,"Volume":7.0,"Open Interest":11,"Bid Stock":109.0,"Ask Stock":111.05,"Last Stock Price":110.025,"Implied Volatility":null,"Expiry_dt":"2026-02-20T00:00:00.000","Years_to_Expiry":0.4298425736,"Forward":28.1657486949,"LogMoneyness":1.4493850883,"IV_bid":null,"IV_ask":null,"IV_mid":null,"IV_spread":null,"Delta":null,"Ivol\/Rvol100d Ratio":null,"Smoothed_IV":null,"TotalVariance":null,"Call Local Vol":null,"Put Local Vol":null,"Realised Vol 100d":0.150987914,"IV_mid_binomial":null},{"Ticker":"WEC","Contract Name":"WEC260417C00120000","Type":"Call","Expiry":"2026-04-17T00:00:00.000","Strike":120.0,"Moneyness":6.9268721359,"Bid":2.1,"Ask":3.6,"Volume":null,"Open Interest":12,"Bid Stock":109.0,"Ask Stock":111.05,"Last Stock Price":110.025,"Implied Volatility":null,"Expiry_dt":"2026-04-17T00:00:00.000","Years_to_Expiry":0.5831622177,"Forward":17.3238364512,"LogMoneyness":1.9354083601,"IV_bid":null,"IV_ask":null,"IV_mid":null,"IV_spread":null,"Delta":null,"Ivol\/Rvol100d Ratio":null,"Smoothed_IV":null,"TotalVariance":null,"Call Local Vol":null,"Put Local Vol":null,"Realised Vol 100d":0.150987914,"IV_mid_binomial":null},{"Ticker":"WEC","Contract Name":"WEC260220P00095000","Type":"Put","Expiry":"2026-02-20T00:00:00.000","Strike":95.0,"Moneyness":3.37289099,"Bid":1.0,"Ask":1.7,"Volume":null,"Open Interest":12,"Bid Stock":109.0,"Ask Stock":111.05,"Last Stock Price":110.025,"Implied Volatility":null,"Expiry_dt":"2026-02-20T00:00:00.000","Years_to_Expiry":0.4298425736,"Forward":28.1657486949,"LogMoneyness":1.2157702372,"IV_bid":null,"IV_ask":null,"IV_mid":null,"IV_spread":null,"Delta":null,"Ivol\/Rvol100d Ratio":null,"Smoothed_IV":null,"TotalVariance":null,"Call Local Vol":null,"Put Local Vol":null,"Realised Vol 100d":0.150987914,"IV_mid_binomial":null},{"Ticker":"WEC","Contract Name":"WEC251219P00097500","Type":"Put","Expiry":"2025-12-19T00:00:00.000","Strike":97.5,"Moneyness":2.0036480476,"Bid":0.7,"Ask":1.25,"Volume":2.0,"Open Interest":37,"Bid Stock":109.0,"Ask Stock":111.05,"Last Stock Price":110.025,"Implied Volatility":null,"Expiry_dt":"2025-12-19T00:00:00.000","Years_to_Expiry":0.257357974,"Forward":48.6612407384,"LogMoneyness":0.6949695429,"IV_bid":null,"IV_ask":null,"IV_mid":null,"IV_spread":null,"Delta":null,"Ivol\/Rvol100d Ratio":null,"Smoothed_IV":null,"TotalVariance":null,"Call Local Vol":null,"Put Local Vol":null,"Realised Vol 100d":0.150987914,"IV_mid_binomial":null},{"Ticker":"WEC","Contract Name":"WEC260116P00095000","Type":"Put","Expiry":"2026-01-16T00:00:00.000","Strike":95.0,"Moneyness":2.4893103203,"Bid":0.7,"Ask":1.1,"Volume":1.0,"Open Interest":17,"Bid Stock":109.0,"Ask Stock":111.05,"Last Stock Price":110.025,"Implied Volatility":null,"Expiry_dt":"2026-01-16T00:00:00.000","Years_to_Expiry":0.334017796,"Forward":38.1631808717,"LogMoneyness":0.9120056923,"IV_bid":null,"IV_ask":null,"IV_mid":null,"IV_spread":null,"Delta":null,"Ivol\/Rvol100d Ratio":null,"Smoothed_IV":null,"TotalVariance":null,"Call Local Vol":null,"Put Local Vol":null,"Realised Vol 100d":0.150987914,"IV_mid_binomial":null},{"Ticker":"WEC","Contract Name":"WEC250919C00110000","Type":"Call","Expiry":"2025-09-19T00:00:00.000","Strike":110.0,"Moneyness":1.0261456688,"Bid":0.65,"Ask":1.7,"Volume":3.0,"Open Interest":735,"Bid Stock":109.0,"Ask Stock":111.05,"Last Stock Price":110.025,"Implied Volatility":null,"Expiry_dt":"2025-09-19T00:00:00.000","Years_to_Expiry":0.0082135524,"Forward":107.1972560447,"LogMoneyness":0.0258097141,"IV_bid":null,"IV_ask":null,"IV_mid":null,"IV_spread":null,"Delta":null,"Ivol\/Rvol100d Ratio":null,"Smoothed_IV":null,"TotalVariance":null,"Call Local Vol":null,"Put Local Vol":null,"Realised Vol 100d":0.150987914,"IV_mid_binomial":null},{"Ticker":"WEC","Contract Name":"WEC251017C00105000","Type":"Call","Expiry":"2025-10-17T00:00:00.000","Strike":105.0,"Moneyness":1.248947672,"Bid":4.9,"Ask":8.6,"Volume":1.0,"Open Interest":57,"Bid Stock":109.0,"Ask Stock":111.05,"Last Stock Price":110.025,"Implied Volatility":null,"Expiry_dt":"2025-10-17T00:00:00.000","Years_to_Expiry":0.0848733744,"Forward":84.0707760284,"LogMoneyness":0.2223013343,"IV_bid":null,"IV_ask":null,"IV_mid":null,"IV_spread":null,"Delta":null,"Ivol\/Rvol100d Ratio":null,"Smoothed_IV":null,"TotalVariance":null,"Call Local Vol":null,"Put Local Vol":null,"Realised Vol 100d":0.150987914,"IV_mid_binomial":null},{"Ticker":"WEC","Contract Name":"WEC260116P00090000","Type":"Put","Expiry":"2026-01-16T00:00:00.000","Strike":90.0,"Moneyness":2.3582939877,"Bid":0.45,"Ask":1.0,"Volume":2.0,"Open Interest":601,"Bid Stock":109.0,"Ask Stock":111.05,"Last Stock Price":110.025,"Implied Volatility":null,"Expiry_dt":"2026-01-16T00:00:00.000","Years_to_Expiry":0.334017796,"Forward":38.1631808717,"LogMoneyness":0.857938471,"IV_bid":null,"IV_ask":null,"IV_mid":null,"IV_spread":null,"Delta":null,"Ivol\/Rvol100d Ratio":null,"Smoothed_IV":null,"TotalVariance":null,"Call Local Vol":null,"Put Local Vol":null,"Realised Vol 100d":0.150987914,"IV_mid_binomial":null},{"Ticker":"WEC","Contract Name":"WEC251017P00100000","Type":"Put","Expiry":"2025-10-17T00:00:00.000","Strike":100.0,"Moneyness":1.1894739733,"Bid":0.2,"Ask":0.3,"Volume":1.0,"Open Interest":31,"Bid Stock":109.0,"Ask Stock":111.05,"Last Stock Price":110.025,"Implied Volatility":null,"Expiry_dt":"2025-10-17T00:00:00.000","Years_to_Expiry":0.0848733744,"Forward":84.0707760284,"LogMoneyness":0.1735111701,"IV_bid":null,"IV_ask":null,"IV_mid":null,"IV_spread":null,"Delta":null,"Ivol\/Rvol100d Ratio":null,"Smoothed_IV":null,"TotalVariance":null,"Call Local Vol":null,"Put Local Vol":null,"Realised Vol 100d":0.150987914,"IV_mid_binomial":null},{"Ticker":"WEC","Contract Name":"WEC260116P00070000","Type":"Put","Expiry":"2026-01-16T00:00:00.000","Strike":70.0,"Moneyness":1.8342286571,"Bid":0.1,"Ask":0.25,"Volume":50.0,"Open Interest":1760,"Bid Stock":109.0,"Ask Stock":111.05,"Last Stock Price":110.025,"Implied Volatility":null,"Expiry_dt":"2026-01-16T00:00:00.000","Years_to_Expiry":0.334017796,"Forward":38.1631808717,"LogMoneyness":0.6066240428,"IV_bid":null,"IV_ask":null,"IV_mid":null,"IV_spread":null,"Delta":null,"Ivol\/Rvol100d Ratio":null,"Smoothed_IV":null,"TotalVariance":null,"Call Local Vol":null,"Put Local Vol":null,"Realised Vol 100d":0.150987914,"IV_mid_binomial":null},{"Ticker":"WEC","Contract Name":"WEC251219C00092500","Type":"Call","Expiry":"2025-12-19T00:00:00.000","Strike":92.5,"Moneyness":1.9008968657,"Bid":13.6,"Ask":16.5,"Volume":3.0,"Open Interest":5,"Bid Stock":109.0,"Ask Stock":111.05,"Last Stock Price":110.025,"Implied Volatility":null,"Expiry_dt":"2025-12-19T00:00:00.000","Years_to_Expiry":0.257357974,"Forward":48.6612407384,"LogMoneyness":0.6423258094,"IV_bid":null,"IV_ask":null,"IV_mid":null,"IV_spread":null,"Delta":null,"Ivol\/Rvol100d Ratio":null,"Smoothed_IV":null,"TotalVariance":null,"Call Local Vol":null,"Put Local Vol":null,"Realised Vol 100d":0.150987914,"IV_mid_binomial":null},{"Ticker":"WEC","Contract Name":"WEC251219C00125000","Type":"Call","Expiry":"2025-12-19T00:00:00.000","Strike":125.0,"Moneyness":2.5687795482,"Bid":0.25,"Ask":0.5,"Volume":2.0,"Open Interest":797,"Bid Stock":109.0,"Ask Stock":111.05,"Last Stock Price":110.025,"Implied Volatility":null,"Expiry_dt":"2025-12-19T00:00:00.000","Years_to_Expiry":0.257357974,"Forward":48.6612407384,"LogMoneyness":0.9434309022,"IV_bid":null,"IV_ask":null,"IV_mid":null,"IV_spread":null,"Delta":null,"Ivol\/Rvol100d Ratio":null,"Smoothed_IV":null,"TotalVariance":null,"Call Local Vol":null,"Put Local Vol":null,"Realised Vol 100d":0.150987914,"IV_mid_binomial":null},{"Ticker":"WEC","Contract Name":"WEC251219C00097500","Type":"Call","Expiry":"2025-12-19T00:00:00.000","Strike":97.5,"Moneyness":2.0036480476,"Bid":10.9,"Ask":14.4,"Volume":2.0,"Open Interest":19,"Bid Stock":109.0,"Ask Stock":111.05,"Last Stock Price":110.025,"Implied Volatility":null,"Expiry_dt":"2025-12-19T00:00:00.000","Years_to_Expiry":0.257357974,"Forward":48.6612407384,"LogMoneyness":0.6949695429,"IV_bid":null,"IV_ask":null,"IV_mid":null,"IV_spread":null,"Delta":null,"Ivol\/Rvol100d Ratio":null,"Smoothed_IV":null,"TotalVariance":null,"Call Local Vol":null,"Put Local Vol":null,"Realised Vol 100d":0.150987914,"IV_mid_binomial":null},{"Ticker":"WEC","Contract Name":"WEC260417C00115000","Type":"Call","Expiry":"2026-04-17T00:00:00.000","Strike":115.0,"Moneyness":6.6382524635,"Bid":3.8,"Ask":4.5,"Volume":null,"Open Interest":6,"Bid Stock":109.0,"Ask Stock":111.05,"Last Stock Price":110.025,"Implied Volatility":null,"Expiry_dt":"2026-04-17T00:00:00.000","Years_to_Expiry":0.5831622177,"Forward":17.3238364512,"LogMoneyness":1.8928487456,"IV_bid":null,"IV_ask":null,"IV_mid":null,"IV_spread":null,"Delta":null,"Ivol\/Rvol100d Ratio":null,"Smoothed_IV":null,"TotalVariance":null,"Call Local Vol":null,"Put Local Vol":null,"Realised Vol 100d":0.150987914,"IV_mid_binomial":null},{"Ticker":"WEC","Contract Name":"WEC260417C00090000","Type":"Call","Expiry":"2026-04-17T00:00:00.000","Strike":90.0,"Moneyness":5.1951541019,"Bid":20.3,"Ask":23.7,"Volume":null,"Open Interest":5,"Bid Stock":109.0,"Ask Stock":111.05,"Last Stock Price":110.025,"Implied Volatility":null,"Expiry_dt":"2026-04-17T00:00:00.000","Years_to_Expiry":0.5831622177,"Forward":17.3238364512,"LogMoneyness":1.6477262876,"IV_bid":null,"IV_ask":null,"IV_mid":null,"IV_spread":null,"Delta":null,"Ivol\/Rvol100d Ratio":null,"Smoothed_IV":null,"TotalVariance":null,"Call Local Vol":null,"Put Local Vol":null,"Realised Vol 100d":0.150987914,"IV_mid_binomial":null},{"Ticker":"WEC","Contract Name":"WEC251219C00087500","Type":"Call","Expiry":"2025-12-19T00:00:00.000","Strike":87.5,"Moneyness":1.7981456838,"Bid":17.4,"Ask":21.5,"Volume":10.0,"Open Interest":11,"Bid Stock":109.0,"Ask Stock":111.05,"Last Stock Price":110.025,"Implied Volatility":null,"Expiry_dt":"2025-12-19T00:00:00.000","Years_to_Expiry":0.257357974,"Forward":48.6612407384,"LogMoneyness":0.5867559582,"IV_bid":null,"IV_ask":null,"IV_mid":null,"IV_spread":null,"Delta":null,"Ivol\/Rvol100d Ratio":null,"Smoothed_IV":null,"TotalVariance":null,"Call Local Vol":null,"Put Local Vol":null,"Realised Vol 100d":0.150987914,"IV_mid_binomial":null},{"Ticker":"WEC","Contract Name":"WEC251219P00100000","Type":"Put","Expiry":"2025-12-19T00:00:00.000","Strike":100.0,"Moneyness":2.0550236386,"Bid":0.95,"Ask":1.3,"Volume":2.0,"Open Interest":45,"Bid Stock":109.0,"Ask Stock":111.05,"Last Stock Price":110.025,"Implied Volatility":null,"Expiry_dt":"2025-12-19T00:00:00.000","Years_to_Expiry":0.257357974,"Forward":48.6612407384,"LogMoneyness":0.7202873508,"IV_bid":null,"IV_ask":null,"IV_mid":null,"IV_spread":null,"Delta":null,"Ivol\/Rvol100d Ratio":null,"Smoothed_IV":null,"TotalVariance":null,"Call Local Vol":null,"Put Local Vol":null,"Realised Vol 100d":0.150987914,"IV_mid_binomial":null},{"Ticker":"WEC","Contract Name":"WEC260116C00085000","Type":"Call","Expiry":"2026-01-16T00:00:00.000","Strike":85.0,"Moneyness":2.227277655,"Bid":24.9,"Ask":28.8,"Volume":2.0,"Open Interest":5,"Bid Stock":109.0,"Ask Stock":111.05,"Last Stock Price":110.025,"Implied Volatility":null,"Expiry_dt":"2026-01-16T00:00:00.000","Years_to_Expiry":0.334017796,"Forward":38.1631808717,"LogMoneyness":0.8007800572,"IV_bid":null,"IV_ask":null,"IV_mid":null,"IV_spread":null,"Delta":null,"Ivol\/Rvol100d Ratio":null,"Smoothed_IV":null,"TotalVariance":null,"Call Local Vol":null,"Put Local Vol":null,"Realised Vol 100d":0.150987914,"IV_mid_binomial":null},{"Ticker":"WEC","Contract Name":"WEC251219C00100000","Type":"Call","Expiry":"2025-12-19T00:00:00.000","Strike":100.0,"Moneyness":2.0550236386,"Bid":10.6,"Ask":14.0,"Volume":21.0,"Open Interest":31,"Bid Stock":109.0,"Ask Stock":111.05,"Last Stock Price":110.025,"Implied Volatility":null,"Expiry_dt":"2025-12-19T00:00:00.000","Years_to_Expiry":0.257357974,"Forward":48.6612407384,"LogMoneyness":0.7202873508,"IV_bid":null,"IV_ask":null,"IV_mid":null,"IV_spread":null,"Delta":null,"Ivol\/Rvol100d Ratio":null,"Smoothed_IV":null,"TotalVariance":null,"Call Local Vol":null,"Put Local Vol":null,"Realised Vol 100d":0.150987914,"IV_mid_binomial":null},{"Ticker":"WEC","Contract Name":"WEC260116P00105000","Type":"Put","Expiry":"2026-01-16T00:00:00.000","Strike":105.0,"Moneyness":2.7513429856,"Bid":1.95,"Ask":2.4,"Volume":2.0,"Open Interest":14,"Bid Stock":109.0,"Ask Stock":111.05,"Last Stock Price":110.025,"Implied Volatility":null,"Expiry_dt":"2026-01-16T00:00:00.000","Years_to_Expiry":0.334017796,"Forward":38.1631808717,"LogMoneyness":1.0120891509,"IV_bid":null,"IV_ask":null,"IV_mid":null,"IV_spread":null,"Delta":null,"Ivol\/Rvol100d Ratio":null,"Smoothed_IV":null,"TotalVariance":null,"Call Local Vol":null,"Put Local Vol":null,"Realised Vol 100d":0.150987914,"IV_mid_binomial":null},{"Ticker":"WEC","Contract Name":"WEC251219C00095000","Type":"Call","Expiry":"2025-12-19T00:00:00.000","Strike":95.0,"Moneyness":1.9522724567,"Bid":15.2,"Ask":19.1,"Volume":1.0,"Open Interest":21,"Bid Stock":109.0,"Ask Stock":111.05,"Last Stock Price":110.025,"Implied Volatility":null,"Expiry_dt":"2025-12-19T00:00:00.000","Years_to_Expiry":0.257357974,"Forward":48.6612407384,"LogMoneyness":0.6689940565,"IV_bid":null,"IV_ask":null,"IV_mid":null,"IV_spread":null,"Delta":null,"Ivol\/Rvol100d Ratio":null,"Smoothed_IV":null,"TotalVariance":null,"Call Local Vol":null,"Put Local Vol":null,"Realised Vol 100d":0.150987914,"IV_mid_binomial":null},{"Ticker":"WEC","Contract Name":"WEC260116C00100000","Type":"Call","Expiry":"2026-01-16T00:00:00.000","Strike":100.0,"Moneyness":2.620326653,"Bid":10.9,"Ask":14.9,"Volume":2.0,"Open Interest":100,"Bid Stock":109.0,"Ask Stock":111.05,"Last Stock Price":110.025,"Implied Volatility":null,"Expiry_dt":"2026-01-16T00:00:00.000","Years_to_Expiry":0.334017796,"Forward":38.1631808717,"LogMoneyness":0.9632989867,"IV_bid":null,"IV_ask":null,"IV_mid":null,"IV_spread":null,"Delta":null,"Ivol\/Rvol100d Ratio":null,"Smoothed_IV":null,"TotalVariance":null,"Call Local Vol":null,"Put Local Vol":null,"Realised Vol 100d":0.150987914,"IV_mid_binomial":null},{"Ticker":"WEC","Contract Name":"WEC260116P00097500","Type":"Put","Expiry":"2026-01-16T00:00:00.000","Strike":97.5,"Moneyness":2.5548184866,"Bid":1.5,"Ask":1.8,"Volume":14.0,"Open Interest":14,"Bid Stock":109.0,"Ask Stock":111.05,"Last Stock Price":110.025,"Implied Volatility":null,"Expiry_dt":"2026-01-16T00:00:00.000","Years_to_Expiry":0.334017796,"Forward":38.1631808717,"LogMoneyness":0.9379811787,"IV_bid":null,"IV_ask":null,"IV_mid":null,"IV_spread":null,"Delta":null,"Ivol\/Rvol100d Ratio":null,"Smoothed_IV":null,"TotalVariance":null,"Call Local Vol":null,"Put Local Vol":null,"Realised Vol 100d":0.150987914,"IV_mid_binomial":null},{"Ticker":"WEC","Contract Name":"WEC260116C00095000","Type":"Call","Expiry":"2026-01-16T00:00:00.000","Strike":95.0,"Moneyness":2.4893103203,"Bid":12.8,"Ask":15.6,"Volume":21.0,"Open Interest":22,"Bid Stock":109.0,"Ask Stock":111.05,"Last Stock Price":110.025,"Implied Volatility":null,"Expiry_dt":"2026-01-16T00:00:00.000","Years_to_Expiry":0.334017796,"Forward":38.1631808717,"LogMoneyness":0.9120056923,"IV_bid":null,"IV_ask":null,"IV_mid":null,"IV_spread":null,"Delta":null,"Ivol\/Rvol100d Ratio":null,"Smoothed_IV":null,"TotalVariance":null,"Call Local Vol":null,"Put Local Vol":null,"Realised Vol 100d":0.150987914,"IV_mid_binomial":null},{"Ticker":"WEC","Contract Name":"WEC251219C00085000","Type":"Call","Expiry":"2025-12-19T00:00:00.000","Strike":85.0,"Moneyness":1.7467700928,"Bid":20.8,"Ask":24.7,"Volume":6.0,"Open Interest":19,"Bid Stock":109.0,"Ask Stock":111.05,"Last Stock Price":110.025,"Implied Volatility":null,"Expiry_dt":"2025-12-19T00:00:00.000","Years_to_Expiry":0.257357974,"Forward":48.6612407384,"LogMoneyness":0.5577684213,"IV_bid":null,"IV_ask":null,"IV_mid":null,"IV_spread":null,"Delta":null,"Ivol\/Rvol100d Ratio":null,"Smoothed_IV":null,"TotalVariance":null,"Call Local Vol":null,"Put Local Vol":null,"Realised Vol 100d":0.150987914,"IV_mid_binomial":null},{"Ticker":"WEC","Contract Name":"WEC260220C00110000","Type":"Call","Expiry":"2026-02-20T00:00:00.000","Strike":110.0,"Moneyness":3.9054527253,"Bid":5.6,"Ask":6.3,"Volume":4.0,"Open Interest":7,"Bid Stock":109.0,"Ask Stock":111.05,"Last Stock Price":110.025,"Implied Volatility":null,"Expiry_dt":"2026-02-20T00:00:00.000","Years_to_Expiry":0.4298425736,"Forward":28.1657486949,"LogMoneyness":1.3623737113,"IV_bid":null,"IV_ask":null,"IV_mid":null,"IV_spread":null,"Delta":null,"Ivol\/Rvol100d Ratio":null,"Smoothed_IV":null,"TotalVariance":null,"Call Local Vol":null,"Put Local Vol":null,"Realised Vol 100d":0.150987914,"IV_mid_binomial":null},{"Ticker":"WEC","Contract Name":"WEC260417P00100000","Type":"Put","Expiry":"2026-04-17T00:00:00.000","Strike":100.0,"Moneyness":5.7723934465,"Bid":2.2,"Ask":2.55,"Volume":2.0,"Open Interest":20,"Bid Stock":109.0,"Ask Stock":111.05,"Last Stock Price":110.025,"Implied Volatility":null,"Expiry_dt":"2026-04-17T00:00:00.000","Years_to_Expiry":0.5831622177,"Forward":17.3238364512,"LogMoneyness":1.7530868033,"IV_bid":null,"IV_ask":null,"IV_mid":null,"IV_spread":null,"Delta":null,"Ivol\/Rvol100d Ratio":null,"Smoothed_IV":null,"TotalVariance":null,"Call Local Vol":null,"Put Local Vol":null,"Realised Vol 100d":0.150987914,"IV_mid_binomial":null},{"Ticker":"WEC","Contract Name":"WEC260220C00090000","Type":"Call","Expiry":"2026-02-20T00:00:00.000","Strike":90.0,"Moneyness":3.1953704116,"Bid":19.8,"Ask":22.9,"Volume":null,"Open Interest":20,"Bid Stock":109.0,"Ask Stock":111.05,"Last Stock Price":110.025,"Implied Volatility":null,"Expiry_dt":"2026-02-20T00:00:00.000","Years_to_Expiry":0.4298425736,"Forward":28.1657486949,"LogMoneyness":1.1617030159,"IV_bid":null,"IV_ask":null,"IV_mid":null,"IV_spread":null,"Delta":null,"Ivol\/Rvol100d Ratio":null,"Smoothed_IV":null,"TotalVariance":null,"Call Local Vol":null,"Put Local Vol":null,"Realised Vol 100d":0.150987914,"IV_mid_binomial":null},{"Ticker":"WEC","Contract Name":"WEC251219C00090000","Type":"Call","Expiry":"2025-12-19T00:00:00.000","Strike":90.0,"Moneyness":1.8495212747,"Bid":19.0,"Ask":21.9,"Volume":5.0,"Open Interest":21,"Bid Stock":109.0,"Ask Stock":111.05,"Last Stock Price":110.025,"Implied Volatility":null,"Expiry_dt":"2025-12-19T00:00:00.000","Years_to_Expiry":0.257357974,"Forward":48.6612407384,"LogMoneyness":0.6149268352,"IV_bid":null,"IV_ask":null,"IV_mid":null,"IV_spread":null,"Delta":null,"Ivol\/Rvol100d Ratio":null,"Smoothed_IV":null,"TotalVariance":null,"Call Local Vol":null,"Put Local Vol":null,"Realised Vol 100d":0.150987914,"IV_mid_binomial":null},{"Ticker":"WEC","Contract Name":"WEC260116C00090000","Type":"Call","Expiry":"2026-01-16T00:00:00.000","Strike":90.0,"Moneyness":2.3582939877,"Bid":19.6,"Ask":22.2,"Volume":5.0,"Open Interest":15,"Bid Stock":109.0,"Ask Stock":111.05,"Last Stock Price":110.025,"Implied Volatility":null,"Expiry_dt":"2026-01-16T00:00:00.000","Years_to_Expiry":0.334017796,"Forward":38.1631808717,"LogMoneyness":0.857938471,"IV_bid":null,"IV_ask":null,"IV_mid":null,"IV_spread":null,"Delta":null,"Ivol\/Rvol100d Ratio":null,"Smoothed_IV":null,"TotalVariance":null,"Call Local Vol":null,"Put Local Vol":null,"Realised Vol 100d":0.150987914,"IV_mid_binomial":null},{"Ticker":"WEC","Contract Name":"WEC251017C00115000","Type":"Call","Expiry":"2025-10-17T00:00:00.000","Strike":115.0,"Moneyness":1.3678950693,"Bid":0.65,"Ask":0.85,"Volume":11.0,"Open Interest":448,"Bid Stock":109.0,"Ask Stock":111.05,"Last Stock Price":110.025,"Implied Volatility":null,"Expiry_dt":"2025-10-17T00:00:00.000","Years_to_Expiry":0.0848733744,"Forward":84.0707760284,"LogMoneyness":0.3132731125,"IV_bid":null,"IV_ask":null,"IV_mid":null,"IV_spread":null,"Delta":null,"Ivol\/Rvol100d Ratio":null,"Smoothed_IV":null,"TotalVariance":null,"Call Local Vol":null,"Put Local Vol":null,"Realised Vol 100d":0.150987914,"IV_mid_binomial":null},{"Ticker":"WEC","Contract Name":"WEC251219C00120000","Type":"Call","Expiry":"2025-12-19T00:00:00.000","Strike":120.0,"Moneyness":2.4660283663,"Bid":0.8,"Ask":1.05,"Volume":40.0,"Open Interest":938,"Bid Stock":109.0,"Ask Stock":111.05,"Last Stock Price":110.025,"Implied Volatility":null,"Expiry_dt":"2025-12-19T00:00:00.000","Years_to_Expiry":0.257357974,"Forward":48.6612407384,"LogMoneyness":0.9026089076,"IV_bid":null,"IV_ask":null,"IV_mid":null,"IV_spread":null,"Delta":null,"Ivol\/Rvol100d Ratio":null,"Smoothed_IV":null,"TotalVariance":null,"Call Local Vol":null,"Put Local Vol":null,"Realised Vol 100d":0.150987914,"IV_mid_binomial":null},{"Ticker":"WEC","Contract Name":"WEC251219P00105000","Type":"Put","Expiry":"2025-12-19T00:00:00.000","Strike":105.0,"Moneyness":2.1577748205,"Bid":1.8,"Ask":2.05,"Volume":5.0,"Open Interest":26,"Bid Stock":109.0,"Ask Stock":111.05,"Last Stock Price":110.025,"Implied Volatility":null,"Expiry_dt":"2025-12-19T00:00:00.000","Years_to_Expiry":0.257357974,"Forward":48.6612407384,"LogMoneyness":0.769077515,"IV_bid":null,"IV_ask":null,"IV_mid":null,"IV_spread":null,"Delta":null,"Ivol\/Rvol100d Ratio":null,"Smoothed_IV":null,"TotalVariance":null,"Call Local Vol":null,"Put Local Vol":null,"Realised Vol 100d":0.150987914,"IV_mid_binomial":null},{"Ticker":"WEC","Contract Name":"WEC260116C00115000","Type":"Call","Expiry":"2026-01-16T00:00:00.000","Strike":115.0,"Moneyness":3.0133756509,"Bid":2.5,"Ask":3.0,"Volume":1.0,"Open Interest":124,"Bid Stock":109.0,"Ask Stock":111.05,"Last Stock Price":110.025,"Implied Volatility":null,"Expiry_dt":"2026-01-16T00:00:00.000","Years_to_Expiry":0.334017796,"Forward":38.1631808717,"LogMoneyness":1.1030609291,"IV_bid":null,"IV_ask":null,"IV_mid":null,"IV_spread":null,"Delta":null,"Ivol\/Rvol100d Ratio":null,"Smoothed_IV":null,"TotalVariance":null,"Call Local Vol":null,"Put Local Vol":null,"Realised Vol 100d":0.150987914,"IV_mid_binomial":null},{"Ticker":"WEC","Contract Name":"WEC260116P00100000","Type":"Put","Expiry":"2026-01-16T00:00:00.000","Strike":100.0,"Moneyness":2.620326653,"Bid":1.25,"Ask":1.6,"Volume":2.0,"Open Interest":777,"Bid Stock":109.0,"Ask Stock":111.05,"Last Stock Price":110.025,"Implied Volatility":null,"Expiry_dt":"2026-01-16T00:00:00.000","Years_to_Expiry":0.334017796,"Forward":38.1631808717,"LogMoneyness":0.9632989867,"IV_bid":null,"IV_ask":null,"IV_mid":null,"IV_spread":null,"Delta":null,"Ivol\/Rvol100d Ratio":null,"Smoothed_IV":null,"TotalVariance":null,"Call Local Vol":null,"Put Local Vol":null,"Realised Vol 100d":0.150987914,"IV_mid_binomial":null},{"Ticker":"WEC","Contract Name":"WEC251219P00110000","Type":"Put","Expiry":"2025-12-19T00:00:00.000","Strike":110.0,"Moneyness":2.2605260024,"Bid":3.2,"Ask":3.7,"Volume":3.0,"Open Interest":54,"Bid Stock":109.0,"Ask Stock":111.05,"Last Stock Price":110.025,"Implied Volatility":null,"Expiry_dt":"2025-12-19T00:00:00.000","Years_to_Expiry":0.257357974,"Forward":48.6612407384,"LogMoneyness":0.8155975306,"IV_bid":null,"IV_ask":null,"IV_mid":null,"IV_spread":null,"Delta":null,"Ivol\/Rvol100d Ratio":null,"Smoothed_IV":null,"TotalVariance":null,"Call Local Vol":null,"Put Local Vol":null,"Realised Vol 100d":0.150987914,"IV_mid_binomial":null},{"Ticker":"WEC","Contract Name":"WEC260417C00110000","Type":"Call","Expiry":"2026-04-17T00:00:00.000","Strike":110.0,"Moneyness":6.3496327912,"Bid":6.5,"Ask":7.2,"Volume":4.0,"Open Interest":16,"Bid Stock":109.0,"Ask Stock":111.05,"Last Stock Price":110.025,"Implied Volatility":null,"Expiry_dt":"2026-04-17T00:00:00.000","Years_to_Expiry":0.5831622177,"Forward":17.3238364512,"LogMoneyness":1.8483969831,"IV_bid":null,"IV_ask":null,"IV_mid":null,"IV_spread":null,"Delta":null,"Ivol\/Rvol100d Ratio":null,"Smoothed_IV":null,"TotalVariance":null,"Call Local Vol":null,"Put Local Vol":null,"Realised Vol 100d":0.150987914,"IV_mid_binomial":null},{"Ticker":"WEC","Contract Name":"WEC260116C00120000","Type":"Call","Expiry":"2026-01-16T00:00:00.000","Strike":120.0,"Moneyness":3.1443919836,"Bid":1.15,"Ask":1.45,"Volume":3.0,"Open Interest":887,"Bid Stock":109.0,"Ask Stock":111.05,"Last Stock Price":110.025,"Implied Volatility":null,"Expiry_dt":"2026-01-16T00:00:00.000","Years_to_Expiry":0.334017796,"Forward":38.1631808717,"LogMoneyness":1.1456205435,"IV_bid":null,"IV_ask":null,"IV_mid":null,"IV_spread":null,"Delta":null,"Ivol\/Rvol100d Ratio":null,"Smoothed_IV":null,"TotalVariance":null,"Call Local Vol":null,"Put Local Vol":null,"Realised Vol 100d":0.150987914,"IV_mid_binomial":null},{"Ticker":"WEC","Contract Name":"WEC260417C00105000","Type":"Call","Expiry":"2026-04-17T00:00:00.000","Strike":105.0,"Moneyness":6.0610131189,"Bid":9.7,"Ask":10.7,"Volume":1.0,"Open Interest":26,"Bid Stock":109.0,"Ask Stock":111.05,"Last Stock Price":110.025,"Implied Volatility":null,"Expiry_dt":"2026-04-17T00:00:00.000","Years_to_Expiry":0.5831622177,"Forward":17.3238364512,"LogMoneyness":1.8018769674,"IV_bid":null,"IV_ask":null,"IV_mid":null,"IV_spread":null,"Delta":null,"Ivol\/Rvol100d Ratio":null,"Smoothed_IV":null,"TotalVariance":null,"Call Local Vol":null,"Put Local Vol":null,"Realised Vol 100d":0.150987914,"IV_mid_binomial":null},{"Ticker":"WEC","Contract Name":"WEC260220C00105000","Type":"Call","Expiry":"2026-02-20T00:00:00.000","Strike":105.0,"Moneyness":3.7279321469,"Bid":9.0,"Ask":9.7,"Volume":null,"Open Interest":15,"Bid Stock":109.0,"Ask Stock":111.05,"Last Stock Price":110.025,"Implied Volatility":null,"Expiry_dt":"2026-02-20T00:00:00.000","Years_to_Expiry":0.4298425736,"Forward":28.1657486949,"LogMoneyness":1.3158536957,"IV_bid":null,"IV_ask":null,"IV_mid":null,"IV_spread":null,"Delta":null,"Ivol\/Rvol100d Ratio":null,"Smoothed_IV":null,"TotalVariance":null,"Call Local Vol":null,"Put Local Vol":null,"Realised Vol 100d":0.150987914,"IV_mid_binomial":null},{"Ticker":"WEC","Contract Name":"WEC251017P00105000","Type":"Put","Expiry":"2025-10-17T00:00:00.000","Strike":105.0,"Moneyness":1.248947672,"Bid":0.5,"Ask":0.6,"Volume":3.0,"Open Interest":2131,"Bid Stock":109.0,"Ask Stock":111.05,"Last Stock Price":110.025,"Implied Volatility":null,"Expiry_dt":"2025-10-17T00:00:00.000","Years_to_Expiry":0.0848733744,"Forward":84.0707760284,"LogMoneyness":0.2223013343,"IV_bid":null,"IV_ask":null,"IV_mid":null,"IV_spread":null,"Delta":null,"Ivol\/Rvol100d Ratio":null,"Smoothed_IV":null,"TotalVariance":null,"Call Local Vol":null,"Put Local Vol":null,"Realised Vol 100d":0.150987914,"IV_mid_binomial":null},{"Ticker":"WEC","Contract Name":"WEC251017P00110000","Type":"Put","Expiry":"2025-10-17T00:00:00.000","Strike":110.0,"Moneyness":1.3084213706,"Bid":1.55,"Ask":1.75,"Volume":5.0,"Open Interest":166,"Bid Stock":109.0,"Ask Stock":111.05,"Last Stock Price":110.025,"Implied Volatility":null,"Expiry_dt":"2025-10-17T00:00:00.000","Years_to_Expiry":0.0848733744,"Forward":84.0707760284,"LogMoneyness":0.2688213499,"IV_bid":null,"IV_ask":null,"IV_mid":null,"IV_spread":null,"Delta":null,"Ivol\/Rvol100d Ratio":null,"Smoothed_IV":null,"TotalVariance":null,"Call Local Vol":null,"Put Local Vol":null,"Realised Vol 100d":0.150987914,"IV_mid_binomial":null},{"Ticker":"WEC","Contract Name":"WEC260116C00105000","Type":"Call","Expiry":"2026-01-16T00:00:00.000","Strike":105.0,"Moneyness":2.7513429856,"Bid":8.5,"Ask":9.4,"Volume":4.0,"Open Interest":77,"Bid Stock":109.0,"Ask Stock":111.05,"Last Stock Price":110.025,"Implied Volatility":null,"Expiry_dt":"2026-01-16T00:00:00.000","Years_to_Expiry":0.334017796,"Forward":38.1631808717,"LogMoneyness":1.0120891509,"IV_bid":null,"IV_ask":null,"IV_mid":null,"IV_spread":null,"Delta":null,"Ivol\/Rvol100d Ratio":null,"Smoothed_IV":null,"TotalVariance":null,"Call Local Vol":null,"Put Local Vol":null,"Realised Vol 100d":0.150987914,"IV_mid_binomial":null},{"Ticker":"WEC","Contract Name":"WEC260116C00110000","Type":"Call","Expiry":"2026-01-16T00:00:00.000","Strike":110.0,"Moneyness":2.8823593183,"Bid":5.2,"Ask":5.6,"Volume":2.0,"Open Interest":45,"Bid Stock":109.0,"Ask Stock":111.05,"Last Stock Price":110.025,"Implied Volatility":null,"Expiry_dt":"2026-01-16T00:00:00.000","Years_to_Expiry":0.334017796,"Forward":38.1631808717,"LogMoneyness":1.0586091665,"IV_bid":null,"IV_ask":null,"IV_mid":null,"IV_spread":null,"Delta":null,"Ivol\/Rvol100d Ratio":null,"Smoothed_IV":null,"TotalVariance":null,"Call Local Vol":null,"Put Local Vol":null,"Realised Vol 100d":0.150987914,"IV_mid_binomial":null},{"Ticker":"WEC","Contract Name":"WEC251219C00115000","Type":"Call","Expiry":"2025-12-19T00:00:00.000","Strike":115.0,"Moneyness":2.3632771844,"Bid":2.0,"Ask":2.3,"Volume":32.0,"Open Interest":1824,"Bid Stock":109.0,"Ask Stock":111.05,"Last Stock Price":110.025,"Implied Volatility":null,"Expiry_dt":"2025-12-19T00:00:00.000","Years_to_Expiry":0.257357974,"Forward":48.6612407384,"LogMoneyness":0.8600492932,"IV_bid":null,"IV_ask":null,"IV_mid":null,"IV_spread":null,"Delta":null,"Ivol\/Rvol100d Ratio":null,"Smoothed_IV":null,"TotalVariance":null,"Call Local Vol":null,"Put Local Vol":null,"Realised Vol 100d":0.150987914,"IV_mid_binomial":null},{"Ticker":"WEC","Contract Name":"WEC251017C00110000","Type":"Call","Expiry":"2025-10-17T00:00:00.000","Strike":110.0,"Moneyness":1.3084213706,"Bid":2.95,"Ask":3.3,"Volume":12.0,"Open Interest":495,"Bid Stock":109.0,"Ask Stock":111.05,"Last Stock Price":110.025,"Implied Volatility":null,"Expiry_dt":"2025-10-17T00:00:00.000","Years_to_Expiry":0.0848733744,"Forward":84.0707760284,"LogMoneyness":0.2688213499,"IV_bid":null,"IV_ask":null,"IV_mid":null,"IV_spread":null,"Delta":null,"Ivol\/Rvol100d Ratio":null,"Smoothed_IV":null,"TotalVariance":null,"Call Local Vol":null,"Put Local Vol":null,"Realised Vol 100d":0.150987914,"IV_mid_binomial":null},{"Ticker":"WEC","Contract Name":"WEC251219C00110000","Type":"Call","Expiry":"2025-12-19T00:00:00.000","Strike":110.0,"Moneyness":2.2605260024,"Bid":4.4,"Ask":4.9,"Volume":29.0,"Open Interest":1188,"Bid Stock":109.0,"Ask Stock":111.05,"Last Stock Price":110.025,"Implied Volatility":null,"Expiry_dt":"2025-12-19T00:00:00.000","Years_to_Expiry":0.257357974,"Forward":48.6612407384,"LogMoneyness":0.8155975306,"IV_bid":null,"IV_ask":null,"IV_mid":null,"IV_spread":null,"Delta":null,"Ivol\/Rvol100d Ratio":null,"Smoothed_IV":null,"TotalVariance":null,"Call Local Vol":null,"Put Local Vol":null,"Realised Vol 100d":0.150987914,"IV_mid_binomial":null},{"Ticker":"WEC","Contract Name":"WEC251219C00105000","Type":"Call","Expiry":"2025-12-19T00:00:00.000","Strike":105.0,"Moneyness":2.1577748205,"Bid":8.0,"Ask":8.4,"Volume":10.0,"Open Interest":50,"Bid Stock":109.0,"Ask Stock":111.05,"Last Stock Price":110.025,"Implied Volatility":null,"Expiry_dt":"2025-12-19T00:00:00.000","Years_to_Expiry":0.257357974,"Forward":48.6612407384,"LogMoneyness":0.769077515,"IV_bid":null,"IV_ask":null,"IV_mid":null,"IV_spread":null,"Delta":null,"Ivol\/Rvol100d Ratio":null,"Smoothed_IV":null,"TotalVariance":null,"Call Local Vol":null,"Put Local Vol":null,"Realised Vol 100d":0.150987914,"IV_mid_binomial":null}]